api_helper/__init__.py
api_helper/alembic.py
api_helper/application.py
api_helper/generic.py
api_helper/middlewares.py
api_helper/pattern.py
api_helper/responses.py
api_helper/sentry.py
api_helper/config/__init__.py
api_helper/config/configure.py
api_helper/config/formatter.py
api_helper/config/logger.py
api_helper/database/__init__.py
api_helper/database/mixin.py
api_helper/database/pagination.py
api_helper/errors/__init__.py
api_helper/errors/app_error.py
api_helper/errors/common.py
api_helper/errors/pagination.py
api_helper/types/__init__.py
api_helper/types/pagination.py
iii_api_helper-0.1.5.dist-info/METADATA
iii_api_helper-0.1.5.dist-info/WHEEL
iii_api_helper-0.1.5.dist-info/RECORD
