Metadata-Version: 2.3
Name: iii-api-helper
Version: 0.1.5
Summary: III Common FastAPI base.
Author: allen0099
Classifier: Framework :: AsyncIO
Classifier: Framework :: FastAPI
Classifier: Intended Audience :: Developers
Classifier: Programming Language :: Python
Classifier: Programming Language :: Python :: 3 :: Only
Classifier: Programming Language :: Python :: 3.10
Classifier: Programming Language :: Python :: 3.11
Classifier: Programming Language :: Python :: 3.12
Classifier: Programming Language :: Python :: Implementation :: CPython
Classifier: Programming Language :: Python :: Implementation :: PyPy
Classifier: Topic :: Internet :: WWW/HTTP :: HTTP Servers
Classifier: Topic :: Internet :: WWW/HTTP :: WSGI :: Application
Classifier: Topic :: Internet :: WWW/HTTP :: WSGI :: Server
Classifier: Topic :: Software Development :: Libraries :: Python Modules
Classifier: Topic :: Utilities
Requires-Python: >=3.10
Requires-Dist: arrow
Requires-Dist: fastapi
Requires-Dist: httpx
Requires-Dist: orjson
Requires-Dist: python-dotenv
Requires-Dist: sentry-sdk
Requires-Dist: uvicorn[standard]<=0.28.1,>=0.23.0
Provides-Extra: database
Requires-Dist: alembic>=1.10.0; extra == 'database'
Requires-Dist: sqlalchemy; extra == 'database'
Requires-Dist: sqlmodel; extra == 'database'
